loreley/__main__.py
loreley/cli.py
loreley/config.py
loreley/entrypoints.py
loreley/preflight.py
loreley/api/__init__.py
loreley/api/app.py
loreley/api/deps.py
loreley/api/routers/__init__.py
loreley/api/routers/archive.py
loreley/api/routers/commits.py
loreley/api/routers/experiments.py
loreley/api/routers/graphs.py
loreley/api/routers/health.py
loreley/api/routers/jobs.py
loreley/api/routers/logs.py
loreley/api/routers/repositories.py
loreley/api/schemas/__init__.py
loreley/api/schemas/archive.py
loreley/api/schemas/commits.py
loreley/api/schemas/experiments.py
loreley/api/schemas/graphs.py
loreley/api/schemas/health.py
loreley/api/schemas/jobs.py
loreley/api/schemas/logs.py
loreley/api/schemas/repositories.py
loreley/api/services/__init__.py
loreley/api/services/archive.py
loreley/api/services/commits.py
loreley/api/services/experiments.py
loreley/api/services/graphs.py
loreley/api/services/health.py
loreley/api/services/jobs.py
loreley/api/services/logs.py
loreley/api/services/repositories.py
loreley/core/contracts.py
loreley/core/experiment_config.py
loreley/core/experiments.py
loreley/core/openai_retry.py
loreley/core/map_elites/chunk.py
loreley/core/map_elites/code_embedding.py
loreley/core/map_elites/dimension_reduction.py
loreley/core/map_elites/file_embedding_cache.py
loreley/core/map_elites/map_elites.py
loreley/core/map_elites/preprocess.py
loreley/core/map_elites/repository_files.py
loreley/core/map_elites/repository_state_embedding.py
loreley/core/map_elites/sampler.py
loreley/core/map_elites/snapshot.py
loreley/core/worker/artifacts.py
loreley/core/worker/coding.py
loreley/core/worker/commit_card.py
loreley/core/worker/commit_summary.py
loreley/core/worker/evaluator.py
loreley/core/worker/evolution.py
loreley/core/worker/job_store.py
loreley/core/worker/output_sanitizer.py
loreley/core/worker/planning.py
loreley/core/worker/repository.py
loreley/core/worker/trajectory.py
loreley/core/worker/agent/__init__.py
loreley/core/worker/agent/contracts.py
loreley-0.6.4a0.dist-info/METADATA
loreley-0.6.4a0.dist-info/WHEEL
loreley-0.6.4a0.dist-info/entry_points.txt
loreley-0.6.4a0.dist-info/licenses/LICENSE
loreley-0.6.4a0.dist-info/RECORD
