Metadata-Version: 2.4
Name: loreley
Version: 0.6.4a0
Summary: Whole-repository Quality-Diversity optimization for real git codebases.
Project-URL: Homepage, https://NeapolitanIcecream.github.io/loreley/
Project-URL: Repository, https://github.com/NeapolitanIcecream/loreley
Project-URL: Documentation, https://NeapolitanIcecream.github.io/loreley/
Project-URL: Issues, https://github.com/NeapolitanIcecream/loreley/issues
License-File: LICENSE
Requires-Python: >=3.11
Requires-Dist: dramatiq[redis]>=2.0.0
Requires-Dist: gitpython>=3.1.45
Requires-Dist: loguru>=0.7.3
Requires-Dist: openai>=2.8.1
Requires-Dist: pathspec>=0.12.1
Requires-Dist: psycopg[binary,pool]>=3.2.12
Requires-Dist: pydantic-settings>=2.12.0
Requires-Dist: pydantic>=2.12.4
Requires-Dist: ribs>=0.8.3
Requires-Dist: rich>=14.2.0
Requires-Dist: scikit-learn>=1.7.2
Requires-Dist: sqlalchemy>=2.0.44
Requires-Dist: tenacity>=9.1.2
Requires-Dist: typer>=0.21.1
Provides-Extra: dev
Requires-Dist: mkdocs-material>=9.7.0; extra == 'dev'
Requires-Dist: pymdown-extensions>=10.17.2; extra == 'dev'
Requires-Dist: pytest>=9.0.1; extra == 'dev'
Provides-Extra: ui
Requires-Dist: fastapi>=0.124.4; extra == 'ui'
Requires-Dist: networkx>=3.6.1; extra == 'ui'
Requires-Dist: pandas>=2.3.3; extra == 'ui'
Requires-Dist: plotly>=6.5.0; extra == 'ui'
Requires-Dist: polars>=1.36.1; extra == 'ui'
Requires-Dist: pyvis>=0.3.2; extra == 'ui'
Requires-Dist: streamlit-aggrid>=1.2.1; extra == 'ui'
Requires-Dist: streamlit>=1.52.1; extra == 'ui'
Requires-Dist: uvicorn[standard]>=0.38.0; extra == 'ui'
